renom_q/__init__.py
renom_q/classicalregister.py
renom_q/exception.py
renom_q/quantumcircuit.py
renom_q/quantumregister.py
renom_q/utilitys.py
renom_q/gate/__init__.py
renom_q/gate/barrier.py
renom_q/gate/ccx.py
renom_q/gate/ch.py
renom_q/gate/crz.py
renom_q/gate/cs.py
renom_q/gate/cswap.py
renom_q/gate/cu1.py
renom_q/gate/cu3.py
renom_q/gate/cx.py
renom_q/gate/cy.py
renom_q/gate/cz.py
renom_q/gate/gate_base1.py
renom_q/gate/gate_base2.py
renom_q/gate/h.py
renom_q/gate/id.py
renom_q/gate/measure.py
renom_q/gate/reset.py
renom_q/gate/rx.py
renom_q/gate/ry.py
renom_q/gate/rz.py
renom_q/gate/s.py
renom_q/gate/sdg.py
renom_q/gate/swap.py
renom_q/gate/t.py
renom_q/gate/tdg.py
renom_q/gate/u1.py
renom_q/gate/u2.py
renom_q/gate/u3.py
renom_q/gate/x.py
renom_q/gate/y.py
renom_q/gate/z.py
renom_q/ml/__init__.py
renom_q/ml/qaa.py
renom_q/ml/qae.py
renom_q/ml/qclustering.py
renom_q/ml/qpca.py
renom_q/ml/qsvm.py
renom_q-0.2b2.dist-info/LICENSE.md
renom_q-0.2b2.dist-info/METADATA
renom_q-0.2b2.dist-info/WHEEL
renom_q-0.2b2.dist-info/top_level.txt
renom_q-0.2b2.dist-info/zip-safe
renom_q-0.2b2.dist-info/RECORD
